{
  "users": [
    {
      "name": "yukirang",
      "phone": "2323",
      "email": "rangk@163.com",
      "id": 1,
      "age": 30,
      "companyId": 1
    },
    {
      "name": "yuki",
      "phone": "2323",
      "email": "yukirang@gmail.com",
      "id": 2,
      "age": 30,
      "companyId": 2
    },
    {
      "name": "rang",
      "phone": "2323",
      "email": "rangk@163.com",
      "id": 3,
      "age": 30,
      "companyId": 3
    }
  ],
  "companies": [
    {
      "id": 1,
      "name": "Apple",
      "description": "Apple"
    },
    {
      "id": 2,
      "name": "Baidu",
      "description": "Baidu"
    },
    {
      "id": 3,
      "name": "Ali",
      "description": "Ali"
    }
  ],
  "books": [
    {
      "id": 1,
      "name": "Apple",
      "author": "233",
      "description": "Apple",
      "img": "../assets/logo.png"
    },
    {
      "id": 2,
      "name": "Apple",
      "author": "233",
      "description": "Apple",
      "img": ""
    },
    {
      "id": 3,
      "name": "Apple",
      "author": "233",
      "description": "Apple",
      "img": ""
    }
  ]
}